dddkit/__init__.py
dddkit/py.typed
dddkit/dataclasses/__init__.py
dddkit/dataclasses/aggregates.py
dddkit/dataclasses/changes_handler.py
dddkit/dataclasses/events.py
dddkit/dataclasses/repositories.py
dddkit/pydantic/__init__.py
dddkit/pydantic/aggregates.py
dddkit/pydantic/changes_handler.py
dddkit/pydantic/events.py
dddkit/pydantic/repositories.py
dddkit/stories/__init__.py
dddkit/stories/hooks.py
dddkit/stories/story.py
dddkit-0.3.0.dist-info/METADATA
dddkit-0.3.0.dist-info/WHEEL
dddkit-0.3.0.dist-info/licenses/LICENSE
dddkit-0.3.0.dist-info/RECORD
